perfumeme/__init__.py
perfumeme/main_functions.py
perfumeme/perfume_molecule.py
perfumeme/scraper.py
perfumeme/usable_function.py
perfumeme/utils.py
perfumeme-1.2.4.dist-info/METADATA
perfumeme-1.2.4.dist-info/WHEEL
perfumeme-1.2.4.dist-info/licenses/LICENSE
perfumeme-1.2.4.dist-info/RECORD
