Metadata-Version: 2.4
Name: perfumeme
Version: 1.2.4
Summary: PERFUMEme is a pip-installable package for analysis of odorous molecules giving main properties. It checks if the molecule has a smell,is toxic for the skin and simulates its evaporation trace. Finally, it indicates in which famous perfumes the molecule is present and eventually its odor.
Project-URL: Homepage, https://github.com/mlacrx/PERFUMEme
Project-URL: GitHub_Marie_Lacroix, https://github.com/mlacrx
Project-URL: GitHub_Lilia_Cretegny, https://github.com/lilia-crtny
Project-URL: GitHub_Coline_Lepers, https://github.com/clepers
Author-email: Marie Lacroix <marie.lacroix@epfl.ch>, Lilia Cretegny <lilia.cretegny@epfl.ch>, Coline Lepers <coline.lepers@epfl.ch>
License-Expression: MIT
License-File: LICENSE
Keywords: Odorous molecules,chemical-engineering,chemistry,chemistry-lab,evaporation,fragrance,perfume,smell,toxic
Classifier: Development Status :: 3 - Alpha
Classifier: Intended Audience :: Developers
Classifier: License :: OSI Approved :: MIT License
Classifier: Operating System :: OS Independent
Classifier: Programming Language :: Python
Classifier: Programming Language :: Python :: 3
Classifier: Programming Language :: Python :: 3.8
Classifier: Programming Language :: Python :: 3.9
Classifier: Programming Language :: Python :: 3.10
Classifier: Programming Language :: Python :: 3.11
Requires-Python: >=3.8
Requires-Dist: matplotlib
Requires-Dist: numpy
Requires-Dist: pandas
Requires-Dist: rdkit
Requires-Dist: requests
Provides-Extra: doc
Requires-Dist: furo; extra == 'doc'
Requires-Dist: myst-parser; extra == 'doc'
Requires-Dist: sphinx; extra == 'doc'
Requires-Dist: sphinx-autodoc-typehints; extra == 'doc'
Requires-Dist: sphinx-copybutton; extra == 'doc'
Provides-Extra: test
Requires-Dist: pytest; extra == 'test'
